webtoon_downloader/__init__.py
webtoon_downloader/cmd/cli.py
webtoon_downloader/cmd/exceptions.py
webtoon_downloader/cmd/progress.py
webtoon_downloader/core/__init__.py
webtoon_downloader/core/downloaders/__init__.py
webtoon_downloader/core/downloaders/image.py
webtoon_downloader/core/exceptions.py
webtoon_downloader/core/file.py
webtoon_downloader/core/webtoon/__init__.py
webtoon_downloader/core/webtoon/api.py
webtoon_downloader/core/webtoon/client.py
webtoon_downloader/core/webtoon/downloaders/__init__.py
webtoon_downloader/core/webtoon/downloaders/callbacks.py
webtoon_downloader/core/webtoon/downloaders/chapter.py
webtoon_downloader/core/webtoon/downloaders/comic.py
webtoon_downloader/core/webtoon/downloaders/options.py
webtoon_downloader/core/webtoon/downloaders/result.py
webtoon_downloader/core/webtoon/exporter.py
webtoon_downloader/core/webtoon/extractor.py
webtoon_downloader/core/webtoon/fetchers.py
webtoon_downloader/core/webtoon/models.py
webtoon_downloader/core/webtoon/namer.py
webtoon_downloader/logger.py
webtoon_downloader/storage/__init__.py
webtoon_downloader/storage/exceptions.py
webtoon_downloader/storage/file.py
webtoon_downloader/storage/pdf.py
webtoon_downloader/storage/zip.py
webtoon_downloader/transformers/base.py
webtoon_downloader/transformers/image.py
webtoon_downloader-2.2.0.dist-info/LICENSE
webtoon_downloader-2.2.0.dist-info/METADATA
webtoon_downloader-2.2.0.dist-info/WHEEL
webtoon_downloader-2.2.0.dist-info/entry_points.txt
webtoon_downloader-2.2.0.dist-info/RECORD
