Metadata-Version: 2.3
Name: webtoon_downloader
Version: 2.2.0
Summary: A fast scrapper ⚡ for downloading comics from the Webtoons platform.
Author: Ali Taibi
Author-email: zehinadev@gmail.com
Requires-Python: >=3.10,<4.0
Classifier: Programming Language :: Python :: 3
Classifier: Programming Language :: Python :: 3.10
Classifier: Programming Language :: Python :: 3.11
Classifier: Programming Language :: Python :: 3.12
Classifier: Programming Language :: Python :: 3.13
Requires-Dist: aiofiles (>=23.2.1,<24.0.0)
Requires-Dist: beautifulsoup4 (>=4.12.2,<5.0.0)
Requires-Dist: dacite (>=1.9.2,<2.0.0)
Requires-Dist: furl (>=2.1.3,<3.0.0)
Requires-Dist: httpx-retries (>=0.4.0,<0.5.0)
Requires-Dist: httpx[http2] (>=0.28.1,<0.29.0)
Requires-Dist: lxml (>=5.3.1,<6.0.0)
Requires-Dist: pillow (>=10.1.0,<11.0.0)
Requires-Dist: pymupdf (>=1.23.8,<2.0.0)
Requires-Dist: rich (>=13.7.0,<14.0.0)
Requires-Dist: rich-click (>=1.7.2,<2.0.0)
Requires-Dist: typing-extensions (>=4.9.0,<5.0.0)
Project-URL: Documentation, https://Zehina.github.io/webtoon-downloader/
Project-URL: Repository, https://github.com/Zehina/webtoon-downloader
